phoenix_tracer/__init__.py
phoenix_tracer/py.typed
phoenix_tracer/tracer.py
phoenix_tracer-0.1.0.dist-info/METADATA
phoenix_tracer-0.1.0.dist-info/WHEEL
phoenix_tracer-0.1.0.dist-info/RECORD
