Metadata-Version: 2.4
Name: phoenix-tracer
Version: 0.1.0
Summary: Add your description here
Author-email: ailadin <korzhukandrew@gmail.com>
Requires-Python: >=3.12
Requires-Dist: arize-phoenix>=8.20.0
